dtwentyORM/BasicElement.py
dtwentyORM/DBConnector.py
dtwentyORM/Element.py
dtwentyORM/Error.py
dtwentyORM/GraphClassFactory.py
dtwentyORM/Metadata.py
dtwentyORM/__init__.py
dtwentyORM/__version__.py
dtwentyORM/support.py
d20_orm-2.0.1.dist-info/LICENSE
d20_orm-2.0.1.dist-info/METADATA
d20_orm-2.0.1.dist-info/WHEEL
d20_orm-2.0.1.dist-info/top_level.txt
d20_orm-2.0.1.dist-info/RECORD
