Metadata-Version: 2.1
Name: d20-orm
Version: 2.0.1
Summary: A small ORM for multimodel DBs
Home-page: https://github.com/d20services/arangodb_python_orm
Author: Alex Sánchez Vega
Author-email: alex@d20.services
Project-URL: Bug Tracker, https://github.com/d20services/arangodb_python_orm/issues
Classifier: Programming Language :: Python :: 3
Classifier: License :: OSI Approved :: MIT License
Classifier: Operating System :: OS Independent
Requires-Python: >=3.8
License-File: LICENSE
Requires-Dist: pyArango
Requires-Dist: datetime
